blqs/__init__.py
blqs/_ast.py
blqs/_ast_test.py
blqs/_namer.py
blqs/_namer_test.py
blqs/_stack.py
blqs/_stack_test.py
blqs/_template.py
blqs/_template_test.py
blqs/_version.py
blqs/assignment.py
blqs/assignment_test.py
blqs/block.py
blqs/block_stack.py
blqs/block_stack_test.py
blqs/block_test.py
blqs/build.py
blqs/build_test.py
blqs/conditional.py
blqs/conditional_test.py
blqs/decorators.py
blqs/decorators_test.py
blqs/delete.py
blqs/delete_test.py
blqs/exceptions.py
blqs/exceptions_test.py
blqs/instruction.py
blqs/instruction_test.py
blqs/iterable.py
blqs/iterable_test.py
blqs/loops.py
blqs/loops_test.py
blqs/op.py
blqs/op_test.py
blqs/program.py
blqs/program_test.py
blqs/protocols.py
blqs/protocols_test.py
blqs/register.py
blqs/register_test.py
blqs/statement.py
blqs/statement_test.py
blqs/testing_samples.py
blqs-0.1.0.dist-info/METADATA
blqs-0.1.0.dist-info/WHEEL
blqs-0.1.0.dist-info/top_level.txt
blqs-0.1.0.dist-info/RECORD
