Metadata-Version: 2.1
Name: blqs
Version: 0.1.0
Summary: Python building blocks for internal domain specific languages.
Home-page: https://github.com/ionq/blqs
Author: The Blqs Developers
Author-email: dabacon@gmail.com
License: Apache 2
Platform: UNKNOWN
Requires-Python: >=3.7.0
Requires-Dist: astor
Requires-Dist: astunparse
Requires-Dist: gast
Requires-Dist: pymore
Requires-Dist: pytype
Requires-Dist: typing-extensions ; python_version < "3.8"
